modules/Attention.py
modules/CoreLayers.py
modules/Decoding.py
modules/Encoding.py
modules/PositionalEncoding.py
modules/Transformer.py
modules/TransformerLRScheduler.py
modules/__init__.py
modules/utils/__init__.py
modules/utils/mask_utils.py
modules/utils/weights_utils.py
torch_transformer/Attention.py
torch_transformer/CoreLayers.py
torch_transformer/Decoding.py
torch_transformer/Encoding.py
torch_transformer/PositionalEncoding.py
torch_transformer/Transformer.py
torch_transformer/TransformerLRScheduler.py
torch_transformer/__init__.py
torch_transformer/utils/__init__.py
torch_transformer/utils/mask_utils.py
torch_transformer/utils/weights_utils.py
torch_transformers/Attention.py
torch_transformers/CoreLayers.py
torch_transformers/Decoding.py
torch_transformers/Encoding.py
torch_transformers/PositionalEncoding.py
torch_transformers/Transformer.py
torch_transformers/TransformerLRScheduler.py
torch_transformers/__init__.py
torch_transformers/utils/__init__.py
torch_transformers/utils/mask_utils.py
torch_transformers/utils/weights_utils.py
utils/__init__.py
utils/mask_utils.py
utils/weights_utils.py
torch_transformers-1.0.4.dist-info/METADATA
torch_transformers-1.0.4.dist-info/WHEEL
torch_transformers-1.0.4.dist-info/top_level.txt
torch_transformers-1.0.4.dist-info/RECORD
