Metadata-Version: 2.1
Name: torch-transformers
Version: 1.0.4
Summary: An implementation of Transformers using PyTorch
Home-page: https://github.com/UltraSpecialException/torch-transformers
Author: Tony Nguyen
Author-email: tonyn0603@gmail.com
License: UNKNOWN
Platform: UNKNOWN
Classifier: Programming Language :: Python :: 3
Requires-Python: >=3.6
